paco/adapters/__init__.py
paco/adapters/monitoring.py
paco/application/__init__.py
paco/application/app_engine.py
paco/application/ec2_launch_manager.py
paco/application/ec2lm_commands.py
paco/application/ec2lm_scripts.py
paco/application/res_engine.py
paco/application/reseng_acm.py
paco/application/reseng_apigatewayrestapi.py
paco/application/reseng_asg.py
paco/application/reseng_cloudfront.py
paco/application/reseng_codedeployapplication.py
paco/application/reseng_cognito.py
paco/application/reseng_dashboard.py
paco/application/reseng_deploymentpipeline.py
paco/application/reseng_dynamodb.py
paco/application/reseng_ebs.py
paco/application/reseng_ec2.py
paco/application/reseng_ec2flowlog.py
paco/application/reseng_ecrreplicationconfiguration.py
paco/application/reseng_ecrrepository.py
paco/application/reseng_ecscluster.py
paco/application/reseng_ecsservices.py
paco/application/reseng_efs.py
paco/application/reseng_eip.py
paco/application/reseng_elasticacheredis.py
paco/application/reseng_elasticsearch.py
paco/application/reseng_eventsrule.py
paco/application/reseng_iamrole.py
paco/application/reseng_iamuser.py
paco/application/reseng_iotanalyticspipeline.py
paco/application/reseng_iotpolicy.py
paco/application/reseng_iottopicrule.py
paco/application/reseng_lambda.py
paco/application/reseng_lb.py
paco/application/reseng_pinpointapplication.py
paco/application/reseng_rds.py
paco/application/reseng_s3bucket.py
paco/application/reseng_snstopic.py
paco/application/reseng_wafwebacl.py
paco/aws_api/acm/ACM.py
paco/aws_api/acm/__init__.py
paco/aws_api/acm/aws_helpers.py
paco/aws_api/awslambda/__init__.py
paco/aws_api/awslambda/code.py
paco/aws_api/ecs/__init__.py
paco/aws_api/ecs/capacityprovider.py
paco/aws_api/iam/__init__.py
paco/aws_api/iam/user.py
paco/aws_api/iot/__init__.py
paco/aws_api/iot/iotpolicy.py
paco/aws_api/ssm/__init__.py
paco/aws_api/ssm/document.py
paco/cftemplates/__init__.py
paco/cftemplates/apigateway.py
paco/cftemplates/appconfig.py
paco_cloud-9.3.45.dist-info/LICENSE
paco_cloud-9.3.45.dist-info/METADATA
paco_cloud-9.3.45.dist-info/WHEEL
paco_cloud-9.3.45.dist-info/entry_points.txt
paco_cloud-9.3.45.dist-info/top_level.txt
paco_cloud-9.3.45.dist-info/RECORD
