Metadata-Version: 2.1
Name: paco-cloud
Version: 9.3.45
Summary: Paco: Prescribed automation for cloud orchestration
Home-page: https://github.com/waterbear-cloud/paco
Author: Waterbear Cloud
Author-email: hello@waterbear.cloud
License: UNKNOWN
Keywords: AWS,Waterbear,Cloud,Infrastructure as Code,CloudFormation
Platform: UNKNOWN
Classifier: Intended Audience :: Developers
Classifier: Programming Language :: Python
Classifier: Programming Language :: Python :: 3.6
Classifier: Programming Language :: Python :: 3.7
Classifier: Programming Language :: Python :: 3.8
Classifier: License :: OSI Approved :: Mozilla Public License 2.0 (MPL 2.0)
Requires-Dist: paco.models (>=7.8.36)
Requires-Dist: boto3 (>=1.16.48)
Requires-Dist: click
Requires-Dist: cookiecutter
Requires-Dist: Setuptools
Requires-Dist: tldextract
Requires-Dist: pexpect
Requires-Dist: troposphere (>=3.2.2)
Requires-Dist: awacs
Requires-Dist: deepdiff (>=4.3.2)
Requires-Dist: gitpython
Requires-Dist: parliament
Requires-Dist: Chameleon
Provides-Extra: docs
Requires-Dist: Sphinx (>=1.3.5) ; extra == 'docs'
Requires-Dist: sphinx-rtd-theme ; extra == 'docs'
